odoo/addons/website_helpdesk_mgmt/README.rst
odoo/addons/website_helpdesk_mgmt/__init__.py
odoo/addons/website_helpdesk_mgmt/__manifest__.py
odoo/addons/website_helpdesk_mgmt/data/ir_model_data.xml
odoo/addons/website_helpdesk_mgmt/i18n/es.po
odoo/addons/website_helpdesk_mgmt/i18n/website_helpdesk_mgmt.pot
odoo/addons/website_helpdesk_mgmt/readme/CONTRIBUTORS.rst
odoo/addons/website_helpdesk_mgmt/readme/DESCRIPTION.rst
odoo/addons/website_helpdesk_mgmt/static/description/icon.png
odoo/addons/website_helpdesk_mgmt/static/description/index.html
odoo13_addon_website_helpdesk_mgmt-13.0.1.0.1.dev4.dist-info/METADATA
odoo13_addon_website_helpdesk_mgmt-13.0.1.0.1.dev4.dist-info/WHEEL
odoo13_addon_website_helpdesk_mgmt-13.0.1.0.1.dev4.dist-info/top_level.txt
odoo13_addon_website_helpdesk_mgmt-13.0.1.0.1.dev4.dist-info/RECORD
